tron/__init__.py
tron/actioncommand.py
tron/command_context.py
tron/crash_reporter.py
tron/default_config.yaml
tron/event.py
tron/eventloop.py
tron/logging.conf
tron/mcp.py
tron/named_config_template.yaml
tron/node.py
tron/scheduler.py
tron/ssh.py
tron/trondaemon.py
tron/api/__init__.py
tron/api/adapter.py
tron/api/controller.py
tron/api/requestargs.py
tron/api/resource.py
tron/commands/__init__.py
tron/commands/client.py
tron/commands/cmd_utils.py
tron/commands/display.py
tron/config/__init__.py
tron/config/config_parse.py
tron/config/config_utils.py
tron/config/manager.py
tron/config/schedule_parse.py
tron/config/schema.py
tron/core/__init__.py
tron/core/action.py
tron/core/actiongraph.py
tron/core/actionrun.py
tron/core/job.py
tron/core/jobrun.py
tron/core/service.py
tron/core/serviceinstance.py
tron/serialize/__init__.py
tron/serialize/filehandler.py
tron/serialize/runstate/__init__.py
tron/serialize/runstate/mongostore.py
tron/serialize/runstate/shelvestore.py
tron/serialize/runstate/sqlalchemystore.py
tron/serialize/runstate/statemanager.py
tron/serialize/runstate/yamlstore.py
tron/utils/__init__.py
tron/utils/collections.py
tron/utils/crontab.py
tron/utils/dicts.py
tron/utils/emailer.py
tron/utils/flockfile.py
tron/utils/iteration.py
tron/utils/observer.py
tron/utils/proxy.py
tron/utils/state.py
tron/utils/timeutils.py
tron/utils/tool_utils.py
tron/utils/trontimespec.py
tron/utils/twistedutils.py
tron-0.6.2.0.data/scripts/action_runner.py
tron-0.6.2.0.data/scripts/action_status.py
tron-0.6.2.0.data/scripts/tronctl
tron-0.6.2.0.data/scripts/trond
tron-0.6.2.0.data/scripts/tronfig
tron-0.6.2.0.data/scripts/tronview
tron-0.6.2.0.dist-info/DESCRIPTION.rst
tron-0.6.2.0.dist-info/METADATA
tron-0.6.2.0.dist-info/RECORD
tron-0.6.2.0.dist-info/WHEEL
tron-0.6.2.0.dist-info/metadata.json
tron-0.6.2.0.dist-info/top_level.txt
tronweb/index.html
tronweb/tronweb.ico
tronweb/css/bootstrap-responsive.min.css
tronweb/css/bootstrap.min.css
tronweb/css/codemirror.css
tronweb/css/tronweb.less
tronweb/css/whhg.css
tronweb/fonts/SIL OFL Font License WebHostingHub Glyphs.txt
