Metadata-Version: 2.0
Name: tron
Version: 0.6.2.0
Summary: Job scheduling and monitoring system
Home-page: http://github.com/Yelp/Tron
Author: Yelp
Author-email: yelplabs@yelp.com
License: UNKNOWN
Platform: UNKNOWN
Classifier: Programming Language :: Python
Classifier: Programming Language :: Python :: 2.5
Classifier: Programming Language :: Python :: 2.6
Classifier: Operating System :: OS Independent
Classifier: License :: OSI Approved :: Apache Software License
Classifier: Topic :: System :: Monitoring
Classifier: Topic :: System :: Systems Administration
Classifier: Intended Audience :: Developers
Classifier: Intended Audience :: System Administrators
Classifier: Development Status :: 4 - Beta
Provides: tron
Requires-Dist: PyYAML (>=3.0)
Requires-Dist: Twisted (<=12.3,>=10.0.0)
Requires-Dist: lockfile (>=0.7)
Requires-Dist: pyasn1 (>=0.0.13)
Requires-Dist: pycrypto (>=2.4)
Requires-Dist: python-daemon (>=1.5.2)
Requires-Dist: pytz (>=2011n)
